{
  "heartbeat_file": "heartbeat.paper7-wave10-mgr-hard-symbols.json",
  "lane": "paper7-wave10/hard-symbol-manager",
  "lane_claim": "Paper 7 wave10 SECTION MANAGER. Enforce strict symbol-inhabitation contract for three leaf workers. Reject docs-only/audit/blocker-map/scaffold outputs. Do not spawn descendants except through AO runner/status files. Manager must inspect worker outputs, run or quote targeted validation, and report only inhabited symbol, exact typed failure, or authority boundary. Targets: NaturalP2ConvergencePromotionAuthorityToken, missingCovariantDerivativeExtendsSelectedExteriorDerivative, missingValuationEinsteinSourceCouplingLaw.",
  "orchestrator_id": "paper7-wave10-mgr-hard-symbols",
  "parent_orchestrator_id": null,
  "status_file": "status.paper7-wave10-mgr-hard-symbols.json",
  "timestamp": "2026-05-19T17:19:17Z"
}
