{
  "artifact_schema": "dashi.dyturbo.t43_direct_strict_log.v1",
  "denominator_dat": "temp-DOWNLOADED/dyturbo/run_cms_smoke/tmp_dyturbo_t43_den_resonly_main.dat",
  "denominator_xs_qt": [
    1211.93,
    3970.08,
    5875.69,
    8020.52,
    9982.38,
    9006.89,
    14976.0,
    13056.7,
    34596.9,
    39932.7,
    45951.1,
    52703.7,
    49495.9,
    85516.4,
    97479.6,
    97756.6,
    32304.8,
    115.404
  ],
  "failure_reason": "DYTurbo xs_qt has non-positive bins; increase statistics or change provider settings",
  "n_bins": 18,
  "non_positive_denominator_bins": [],
  "non_positive_numerator_bins": [
    17
  ],
  "numerator_dat": "temp-DOWNLOADED/dyturbo/run_cms_smoke/tmp_dyturbo_t43_num_resonly_main.dat",
  "numerator_xs_qt": [
    49.1816,
    158.679,
    240.697,
    299.129,
    401.105,
    420.623,
    511.669,
    494.638,
    1317.53,
    1408.86,
    1385.63,
    1376.2,
    1136.09,
    2027.85,
    1904.37,
    1630.39,
    332.477,
    0.0
  ],
  "promotes": false,
  "status": "blocked",
  "strict_artifact": "scripts/data/outputs/t43_strict_log_sigma_dashi_v4_20260515.json"
}
